mpl_image_labeller/__init__.py
mpl_image_labeller/_labeller.py
mpl_image_labeller/_util.py
mpl_image_labeller/_version.py
mpl_image_labeller/_widgets.py
mpl_image_labeller-1.1.2.dist-info/LICENSE
mpl_image_labeller-1.1.2.dist-info/METADATA
mpl_image_labeller-1.1.2.dist-info/WHEEL
mpl_image_labeller-1.1.2.dist-info/top_level.txt
mpl_image_labeller-1.1.2.dist-info/RECORD
