Metadata-Version: 2.1
Name: mpl-image-labeller
Version: 1.1.2
Summary: Use interactive matplotlib to label images for classification
Home-page: https://mpl-image-labeller.rtfd.io
Author: Ian Hunt-Isaak
Author-email: ianhuntisaak@gmail.com
License: BSD-3-Clause
Project-URL: Tracker, https://github.com/ianhi/mpl-image-labeller/issues
Project-URL: Changelog, https://github.com/ianhi/mpl-image-labeller/releases
Project-URL: Documentation, https://mpl-image-labeller.rtfd.io
Project-URL: Source, https://github.com/ianhi/mpl-interactions
Classifier: Development Status :: 5 - Production/Stable
Classifier: Framework :: Matplotlib
Classifier: License :: OSI Approved :: BSD License
Classifier: Natural Language :: English
Classifier: Programming Language :: Python :: 3
Classifier: Programming Language :: Python :: 3 :: Only
Classifier: Programming Language :: Python :: 3.7
Classifier: Programming Language :: Python :: 3.8
Classifier: Programming Language :: Python :: 3.9
Classifier: Programming Language :: Python :: Implementation :: CPython
Requires-Python: >=3.7
License-File: LICENSE
Requires-Dist: matplotlib
Provides-Extra: dev
Requires-Dist: black ; extra == 'dev'
Requires-Dist: flake8 ; extra == 'dev'
Requires-Dist: flake8-docstrings ; extra == 'dev'
Requires-Dist: ipython ; extra == 'dev'
Requires-Dist: isort ; extra == 'dev'
Requires-Dist: jedi (<0.18.0) ; extra == 'dev'
Requires-Dist: mypy ; extra == 'dev'
Requires-Dist: pre-commit ; extra == 'dev'
Requires-Dist: pydocstyle ; extra == 'dev'
Requires-Dist: pytest ; extra == 'dev'
Provides-Extra: doc
Requires-Dist: Sphinx (>=1.5) ; extra == 'doc'
Requires-Dist: jupyter-sphinx ; extra == 'doc'
Requires-Dist: myst-nb ; extra == 'doc'
Requires-Dist: numpydoc ; extra == 'doc'
Requires-Dist: sphinx-book-theme ; extra == 'doc'
Requires-Dist: sphinx-copybutton ; extra == 'doc'
Requires-Dist: sphinx-panels ; extra == 'doc'
Requires-Dist: sphinx-thebe ; extra == 'doc'
Requires-Dist: sphinx-togglebutton ; extra == 'doc'
Provides-Extra: testing
Requires-Dist: pytest ; extra == 'testing'
